slt_datasets/SLTDataset.py
slt_datasets/WordLevelTokenizer.py
slt_datasets/__init__.py
slt_datasets/dataset_comparison.ipynb
slt_datasets-0.0.2rc45.post1.dist-info/LICENSE
slt_datasets-0.0.2rc45.post1.dist-info/WHEEL
slt_datasets-0.0.2rc45.post1.dist-info/METADATA
slt_datasets-0.0.2rc45.post1.dist-info/RECORD
